{
  "main": {
    "id": "166d3888b1c88c9b",
    "type": "split",
    "children": [
      {
        "id": "3190c09adc409a4b",
        "type": "tabs",
        "children": [
          {
            "id": "5a56b322d0d77792",
            "type": "leaf",
            "state": {
              "type": "markdown",
              "state": {
                "file": "COMP604/Basic command line.md",
                "mode": "source",
                "source": false
              },
              "icon": "lucide-file",
              "title": "Basic command line"
            }
          },
          {
            "id": "230fc4ea80430600",
            "type": "leaf",
            "state": {
              "type": "markdown",
              "state": {
                "file": "COMP610/Algorithm.md",
                "mode": "source",
                "source": false
              },
              "icon": "lucide-file",
              "title": "Algorithm"
            }
          },
          {
            "id": "a6d55099d64ca892",
            "type": "leaf",
            "state": {
              "type": "markdown",
              "state": {
                "file": "COMP610/Algorithm.md",
                "mode": "source",
                "source": false
              },
              "icon": "lucide-file",
              "title": "Algorithm"
            }
          },
          {
            "id": "d8d45ea47a639627",
            "type": "leaf",
            "state": {
              "type": "markdown",
              "state": {
                "file": "COMP610/Big O notation.md",
                "mode": "source",
                "source": false
              },
              "icon": "lucide-file",
              "title": "Big O notation"
            }
          },
          {
            "id": "1eb001131551f78c",
            "type": "leaf",
            "state": {
              "type": "markdown",
              "state": {
                "file": "COMP610/Collections.md",
                "mode": "source",
                "source": false
              },
              "icon": "lucide-file",
              "title": "Collections"
            }
          },
          {
            "id": "248c448a737a7e8d",
            "type": "leaf",
            "state": {
              "type": "markdown",
              "state": {
                "file": "COMP610/Generics.md",
                "mode": "source",
                "source": false
              },
              "icon": "lucide-file",
              "title": "Generics"
            }
          },
          {
            "id": "0d7039192fefcba9",
            "type": "leaf",
            "state": {
              "type": "markdown",
              "state": {
                "file": "COMP607/Hackers.md",
                "mode": "source",
                "source": false
              },
              "icon": "lucide-file",
              "title": "Hackers"
            }
          },
          {
            "id": "4099387b40d22c5a",
            "type": "leaf",
            "state": {
              "type": "markdown",
              "state": {
                "file": "COMP607/Five Principles of Information Security.md",
                "mode": "source",
                "source": false
              },
              "icon": "lucide-file",
              "title": "Five Principles of Information Security"
            }
          },
          {
            "id": "b4b881c4870b32f4",
            "type": "leaf",
            "state": {
              "type": "markdown",
              "state": {
                "file": "COMP607/Asymmetric Encryption.md",
                "mode": "source",
                "source": false
              },
              "icon": "lucide-file",
              "title": "Asymmetric Encryption"
            }
          },
          {
            "id": "2e093898ffead6c9",
            "type": "leaf",
            "state": {
              "type": "markdown",
              "state": {
                "file": "COMP607/Asymmetric Encryption.md",
                "mode": "source",
                "source": false
              },
              "icon": "lucide-file",
              "title": "Asymmetric Encryption"
            }
          },
          {
            "id": "5a4f2ee60adf97a7",
            "type": "leaf",
            "state": {
              "type": "markdown",
              "state": {
                "file": "COMP607/Five Principles of Information Security.md",
                "mode": "source",
                "source": false
              },
              "icon": "lucide-file",
              "title": "Five Principles of Information Security"
            }
          },
          {
            "id": "18ca332a4a6c9d4f",
            "type": "leaf",
            "state": {
              "type": "markdown",
              "state": {
                "file": "COMP607/Hackers.md",
                "mode": "source",
                "source": false
              },
              "icon": "lucide-file",
              "title": "Hackers"
            }
          },
          {
            "id": "d9339247ece297e5",
            "type": "leaf",
            "state": {
              "type": "markdown",
              "state": {
                "file": "COMP607/Malicious programs.md",
                "mode": "source",
                "source": false
              },
              "icon": "lucide-file",
              "title": "Malicious programs"
            }
          },
          {
            "id": "2d9adf54f670fe75",
            "type": "leaf",
            "state": {
              "type": "markdown",
              "state": {
                "file": "COMP607/Authentication, Authorisation, and Accounting (AAA).md",
                "mode": "source",
                "source": false
              },
              "icon": "lucide-file",
              "title": "Authentication, Authorisation, and Accounting (AAA)"
            }
          },
          {
            "id": "156813a61759f8f5",
            "type": "leaf",
            "state": {
              "type": "markdown",
              "state": {
                "file": "COMP607/Standard Biometrics.md",
                "mode": "source",
                "source": false
              },
              "icon": "lucide-file",
              "title": "Standard Biometrics"
            }
          },
          {
            "id": "4e08d18771086160",
            "type": "leaf",
            "state": {
              "type": "markdown",
              "state": {
                "file": "COMP607/Standalone vs Controller APs.md",
                "mode": "source",
                "source": false
              },
              "icon": "lucide-file",
              "title": "Standalone vs Controller APs"
            }
          },
          {
            "id": "b8eadabdd484c4c5",
            "type": "leaf",
            "state": {
              "type": "markdown",
              "state": {
                "file": "COMP607/Network Blurred Edges.md",
                "mode": "source",
                "source": false
              },
              "icon": "lucide-file",
              "title": "Network Blurred Edges"
            }
          },
          {
            "id": "b7b069864246cf7a",
            "type": "leaf",
            "state": {
              "type": "markdown",
              "state": {
                "file": "COMP607/Focus.md",
                "mode": "source",
                "source": false
              },
              "icon": "lucide-file",
              "title": "Focus"
            }
          },
          {
            "id": "80f05cf13e61c47e",
            "type": "leaf",
            "state": {
              "type": "markdown",
              "state": {
                "file": "COMP607/Network Blurred Edges.md",
                "mode": "source",
                "source": false
              },
              "icon": "lucide-file",
              "title": "Network Blurred Edges"
            }
          }
        ],
        "currentTab": 18
      }
    ],
    "direction": "vertical"
  },
  "left": {
    "id": "4d16595f64c18a82",
    "type": "split",
    "children": [
      {
        "id": "686b133b1a16207f",
        "type": "tabs",
        "children": [
          {
            "id": "3deee57fba1c68d3",
            "type": "leaf",
            "state": {
              "type": "file-explorer",
              "state": {
                "sortOrder": "alphabetical"
              },
              "icon": "lucide-folder-closed",
              "title": "Files"
            }
          },
          {
            "id": "ce333dd8d56395f4",
            "type": "leaf",
            "state": {
              "type": "search",
              "state": {
                "query": "",
                "matchingCase": false,
                "explainSearch": false,
                "collapseAll": false,
                "extraContext": false,
                "sortOrder": "alphabetical"
              },
              "icon": "lucide-search",
              "title": "Search"
            }
          },
          {
            "id": "4572942067116ada",
            "type": "leaf",
            "state": {
              "type": "bookmarks",
              "state": {},
              "icon": "lucide-bookmark",
              "title": "Bookmarks"
            }
          }
        ]
      }
    ],
    "direction": "horizontal",
    "width": 300
  },
  "right": {
    "id": "6d913500ddc0a1ea",
    "type": "split",
    "children": [
      {
        "id": "b7a2ee73564013f2",
        "type": "tabs",
        "children": [
          {
            "id": "d486a103f472efbd",
            "type": "leaf",
            "state": {
              "type": "backlink",
              "state": {
                "file": "COMP607/Network Blurred Edges.md",
                "collapseAll": false,
                "extraContext": false,
                "sortOrder": "alphabetical",
                "showSearch": false,
                "searchQuery": "",
                "backlinkCollapsed": false,
                "unlinkedCollapsed": true
              },
              "icon": "links-coming-in",
              "title": "Backlinks for Network Blurred Edges"
            }
          },
          {
            "id": "c8b8ba52d52981dd",
            "type": "leaf",
            "state": {
              "type": "outgoing-link",
              "state": {
                "file": "COMP607/Network Blurred Edges.md",
                "linksCollapsed": false,
                "unlinkedCollapsed": true
              },
              "icon": "links-going-out",
              "title": "Outgoing links from Network Blurred Edges"
            }
          },
          {
            "id": "3a3f6455ad14a640",
            "type": "leaf",
            "state": {
              "type": "tag",
              "state": {
                "sortOrder": "frequency",
                "useHierarchy": true
              },
              "icon": "lucide-tags",
              "title": "Tags"
            }
          },
          {
            "id": "a83a2c287734a9da",
            "type": "leaf",
            "state": {
              "type": "outline",
              "state": {
                "file": "COMP607/Network Blurred Edges.md"
              },
              "icon": "lucide-list",
              "title": "Outline of Network Blurred Edges"
            }
          },
          {
            "id": "da47ab1a3d348737",
            "type": "leaf",
            "state": {
              "type": "git-view",
              "state": {},
              "icon": "git-pull-request",
              "title": "Source Control"
            }
          }
        ],
        "currentTab": 4
      }
    ],
    "direction": "horizontal",
    "width": 300,
    "collapsed": true
  },
  "left-ribbon": {
    "hiddenItems": {
      "switcher:Open quick switcher": false,
      "graph:Open graph view": false,
      "canvas:Create new canvas": false,
      "daily-notes:Open today's daily note": false,
      "templates:Insert template": false,
      "command-palette:Open command palette": false,
      "obsidian-git:Open Git source control": false
    }
  },
  "active": "80f05cf13e61c47e",
  "lastOpenFiles": [
    "COMP607/WPA vs WPA2.md",
    "COMP607/Symmetric Encryption.md",
    "COMP607/WLAN Enterprise Attacks.md",
    "COMP607/Worm vs Viruses.md",
    "COMP607/Hackers.md",
    "Images/Pasted image 20241026004625.png",
    "COMP607/Focus.md",
    "COMP607/Standard Biometrics.md",
    "COMP607/Network Blurred Edges.md",
    "COMP607/Standalone vs Controller APs.md",
    "COMP607/Authentication, Authorisation, and Accounting (AAA).md",
    "COMP607/Defenses against attacks.md",
    "COMP607/Five Principles of Information Security.md",
    "COMP607/5 principle of security.md",
    "COMP607/Social Engineering Effectiveness.md",
    "COMP607/Malicious programs.md",
    "COMP607/Hashing.md",
    "COMP607/Asymmetric Encryption.md",
    "Images/Pasted image 20241023164027.png",
    "COMP610/Data Structures.md",
    "COMP610/Big O notation.md",
    "COMP610/Algorithm.md",
    "COMP610/Array.md",
    "COMP603/ArrayList.md",
    "COMP610/Generics.md",
    "LinkedLists.md",
    "List Interface.md",
    "Images/Pasted image 20241010154844.png"
  ]
}